LICENSE
MANIFEST.in
README.md
setup.cfg
setup.py
src/markdownup/__init__.py
src/markdownup/__main__.py
src/markdownup/config.py
src/markdownup/helpers.py
src/markdownup/markdownup.py
src/markdownup/response.py
src/markdownup/theme.py
src/markdownup/wsgi_application.py
src/markdownup.egg-info/PKG-INFO
src/markdownup.egg-info/SOURCES.txt
src/markdownup.egg-info/dependency_links.txt
src/markdownup.egg-info/requires.txt
src/markdownup.egg-info/top_level.txt
src/markdownup/auth/__init__.py
src/markdownup/auth/auth_provider.py
src/markdownup/auth/basicauth/__init__.py
src/markdownup/auth/basicauth/basic_auth.py
src/markdownup/auth/keycloak/__init__.py
src/markdownup/auth/keycloak/keycloak.py
src/markdownup/cache/__init__.py
src/markdownup/cache/cache.py
src/markdownup/cache/__pycache__/__init__.cpython-38.pyc
src/markdownup/cache/__pycache__/__init__.cpython-39.pyc
src/markdownup/cache/__pycache__/cache.cpython-38.pyc
src/markdownup/cache/__pycache__/cache.cpython-39.pyc
src/markdownup/cache/builtin/__init__.py
src/markdownup/cache/builtin/client.py
src/markdownup/cache/builtin/server.py
src/markdownup/cache/redis/__init__.py
src/markdownup/cache/redis/redis_cache.py
src/markdownup/filesystem/__init__.py
src/markdownup/filesystem/asset_file.py
src/markdownup/filesystem/directory.py
src/markdownup/filesystem/entry.py
src/markdownup/filesystem/file.py
src/markdownup/filesystem/markdown_file.py
src/markdownup/search/__init__.py
src/markdownup/search/search_provider.py
src/markdownup/themes/bare/document.html
src/markdownup/themes/bare/search-results.html
src/markdownup/themes/default/404.html
src/markdownup/themes/default/document.html
src/markdownup/themes/default/header-and-menu.html
src/markdownup/themes/default/main.css
src/markdownup/themes/default/menu.html
src/markdownup/themes/default/pygmentize-codehilite.css
src/markdownup/themes/default/relative-time.js
src/markdownup/themes/default/search-results.html