Metadata-Version: 2.1
Name: markdownup
Version: 0.0.54
Summary: Markdown server
Home-page: https://github.com/binokkio/markdownup
Author: Binokkio
Author-email: binokkio@b.nana.technology
License: LGPLv3+
Keywords: markdown,server
Platform: UNKNOWN
License-File: LICENSE
